VideoRAC/__init__.py
VideoRAC/Modules/__init__.py
VideoRAC/Modules/chunking.py
VideoRAC/Modules/qa_generation.py
VideoRAC/utils/__init__.py
VideoRAC/utils/entropy_utils.py
VideoRAC/utils/logging_utils.py
videorac-0.2.7.dist-info/licenses/LICENSE
videorac-0.2.7.dist-info/METADATA
videorac-0.2.7.dist-info/WHEEL
videorac-0.2.7.dist-info/top_level.txt
videorac-0.2.7.dist-info/RECORD
