Metadata-Version: 2.4
Name: VideoRAC
Version: 0.2.7
Summary: Video Retrieval-Augmented Chunking and Q&A Generation Toolkit
Author-email: Melika Shirian <m.shirian@gmail.com>, Kianoosh Vadaei <k.vadaei@eng.ui.ac.ir>, Arshia Hemmat <amirarshia.hemmat@kellogg.ox.ac.uk>, Mohammad Hassan Heydari <heidary0081@gmail.com>, Afsaneh Fatemi <a.fatemi@eng.ui.ac.ir>
License: CC BY 4.0
Project-URL: Homepage, https://prismaticlab.github.io/Video-RAC/
Project-URL: Repository, https://github.com/PrismaticLab/Video-RAC
Project-URL: Issues, https://github.com/PrismaticLab/Video-RAC/issues
Project-URL: Documentation, https://prismaticlab.github.io/Video-RAC/
Keywords: video,rag,chunking,qa,clip,ssim,yt-dlp,multimodal_rag
Classifier: Development Status :: 3 - Alpha
Classifier: Intended Audience :: Science/Research
Classifier: License :: Other/Proprietary License
Classifier: Operating System :: OS Independent
Classifier: Programming Language :: Python
Classifier: Programming Language :: Python :: 3
Classifier: Programming Language :: Python :: 3.9
Classifier: Programming Language :: Python :: 3.10
Classifier: Programming Language :: Python :: 3.11
Classifier: Programming Language :: Python :: 3.12
Classifier: Topic :: Scientific/Engineering :: Artificial Intelligence
Classifier: Topic :: Multimedia :: Video
Requires-Python: >=3.9
License-File: LICENSE
Requires-Dist: opencv-python>=4.7
Requires-Dist: tqdm>=4.65
Requires-Dist: yt-dlp>=2024.8.6
Requires-Dist: youtube-transcript-api>=0.6.2
Requires-Dist: transformers>=4.41
Requires-Dist: scikit-image>=0.22
Requires-Dist: scipy>=1.10
Requires-Dist: langchain>=0.2.0
Requires-Dist: colorlog>=6.9.0
Requires-Dist: Pillow>=9.5
Dynamic: license-file
